<?xml version="1.0" encoding="UTF-8" ?>
<openerp>
	<data>
		<record id="view_company_form_inherit" model="ir.ui.view">
			<field name="name">res.company.form.inherit</field>
			<field name="model">res.company</field>
			<field name="inherit_id" ref="base.view_company_form"/>
			<field name="priority">33</field>
			<field name="type">form</field>
			<field name="arch" type="xml">
				<page string="Configuration" position="inside">
					<separator string="Sales" colspan="4"/>
						<field name="sale_order_footer" colspan="2"/>
						<field name="show_sale_order_footer" colspan="2"/>
				</page>
			</field>
		</record>
		
		<record id="view_order_form_inherit" model="ir.ui.view">
			<field name="name">sale.order.form.inherit</field>
			<field name="model">sale.order</field>
			<field name="inherit_id" ref="sale.view_order_form"/>
			<field name="type">form</field>
			<field name="arch" type="xml">
				<field name="client_order_ref" position="after">
					<field name="expiration_date"/> 
				</field>
			</field>
		</record>
	</data>
</openerp>